README.rst
setup.py
tinnitus/__init__.py
tinnitus/pluggable.py
tinnitus/queue.py
tinnitus/server.py
tinnitus.egg-info/PKG-INFO
tinnitus.egg-info/SOURCES.txt
tinnitus.egg-info/dependency_links.txt
tinnitus.egg-info/entry_points.txt
tinnitus.egg-info/requires.txt
tinnitus.egg-info/top_level.txt
tinnitus/plugins/include.txt
tinnitus/plugins/vlc_backend.py