Metadata-Version: 1.1
Name: tinnitus
Version: 0.1.5
Summary: A pluggable playback queue service
Home-page: https://github.com/strangedev/tinnitus
Author: strangedev
Author-email: strangedev@posteo.net
License: MIT
Download-URL: https://github.com/strangedev/tinnitus/tarball/0.1.5
Keywords: tinnitus audio playback background service
Platform: UNKNOWN
Classifier: Development Status :: 4 - Beta
Classifier: Operating System :: POSIX
Classifier: Operating System :: MacOS
Classifier: Operating System :: Unix
Classifier: Intended Audience :: Developers
Classifier: Topic :: Software Development :: Libraries
Classifier: Topic :: Multimedia :: Sound/Audio
Classifier: Topic :: Multimedia :: Sound/Audio :: Players
Classifier: License :: OSI Approved :: MIT License
Classifier: Programming Language :: Python :: 3.5
Classifier: Programming Language :: Python :: 3.6
Classifier: Programming Language :: Python :: 3 :: Only
